[
  {
    "weapon_category": "Knife",
    "player_name": "BiddynosoundHeadcrabLvl18",
    "steam_id": "30308641",
    "kills": 19
  },
  {
    "weapon_category": "Sniper",
    "player_name": "AimNinnaLvl22",
    "steam_id": "225176809",
    "kills": 9
  },
  {
    "weapon_category": "Pistol",
    "player_name": "coldRPGLvl49",
    "steam_id": "146179965",
    "kills": 5
  },
  {
    "weapon_category": "Pistol",
    "player_name": "EcstatictongsVoidwalkerLvl6",
    "steam_id": "192802928",
    "kills": 3
  },
  {
    "weapon_category": "Pistol",
    "player_name": "ThazPaladinLvl7",
    "steam_id": "25869320",
    "kills": 3
  },
  {
    "weapon_category": "Pistol",
    "player_name": "wheelchairSaboteurLvl33",
    "steam_id": "326879082",
    "kills": 3
  },
  {
    "weapon_category": "Pistol",
    "player_name": "CurrymanDragonKnightLvl33",
    "steam_id": "7541416",
    "kills": 3
  },
  {
    "weapon_category": "Pistol",
    "player_name": "SickboyrariTyrandeWhisperwindLvl33",
    "steam_id": "32783979",
    "kills": 2
  },
  {
    "weapon_category": "Pistol",
    "player_name": "RebelRockGolemLvl10",
    "steam_id": "152859091",
    "kills": 2
  },
  {
    "weapon_category": "Pistol",
    "player_name": "RenDazzleLvl14",
    "steam_id": "1534542",
    "kills": 1
  },
  {
    "weapon_category": "Pistol",
    "player_name": "AimNinnaLvl22",
    "steam_id": "225176809",
    "kills": 1
  },
  {
    "weapon_category": "Pistol",
    "player_name": "DogeJackSkellingtonLvl26",
    "steam_id": "370836478",
    "kills": 1
  },
  {
    "weapon_category": "Pistol",
    "player_name": "you0UndeadScourgeLvl13",
    "steam_id": "431253218",
    "kills": 1
  },
  {
    "weapon_category": "Pistol",
    "player_name": "SensibleDNkMutaliskLvl4",
    "steam_id": "1226709410",
    "kills": 1
  },
  {
    "weapon_category": "Knife",
    "player_name": "TonyColdlightOracleLvl11",
    "steam_id": "32169045",
    "kills": 1
  },
  {
    "weapon_category": "Knife",
    "player_name": "1600microsoftpointsneededWolfLvl11",
    "steam_id": "41176942",
    "kills": 1
  },
  {
    "weapon_category": "Sniper",
    "player_name": "PickMeTrickorTreaterLvl8",
    "steam_id": "249549793",
    "kills": 1
  },
  {
    "weapon_category": "Knife",
    "player_name": "RawrMcRawrPriestessoftheMoonLvl34",
    "steam_id": "20687493",
    "kills": 1
  },
  {
    "weapon_category": "Knife",
    "player_name": "AimNinnaLvl22",
    "steam_id": "225176809",
    "kills": 1
  }
]